Workbook
Name Slicer_Category: #N/A
Name Slicer_Order_Date__Year: #N/A
Name Slicer_Region: #N/A
Name Slicer_Segment: #N/A
Name Slicer_Ship_Mode: #N/A

Sheet Sheet1
A2: Key Performance Indicators (KPIS) | K2: Geographic Analysis | P2: Geographic Analysis | U2: Sales and Profit by Month
K3: Sales and Profit across Regions | P3: Sales and Profit by Year
A4: Sum of Order Value | B4: Sum of Profit | C4: Sum of Quantity | D4: Average of Order Value2 | E4: Profit margin_(%) | F4: Average of Discount Value | G4: Average of Shipping Duration | H4: Count of Order ID | K4: Region | L4: Count of Order ID | M4: Sum of Profit | P4: Order Date (Year) | Q4: Sum of Profit | R4: Count of Order ID | U4: Order Date (Month) | V4: Sum of Profit | W4: Count of Order ID | Z4: Category | AA4: Sum of Profit | AB4: Count of Order ID | AE4: Product Name | AF4: Sum of Quantity | AI4: Product Name | AJ4: Sum of Quantity | AM4: Sub-Category | AN4: Sum of Profit | AO4: Sum of Discount Value | AR4: Segment | AS4: Sum of Profit | AT4: Count of Order ID | AW4: Customer Name | AX4: Count of Order ID | BA4: Ship Mode | BB4: Count of Order ID
A5: 11942478 | B5: 283240 | C5: 30354 | D5: 1484.0907 | E5: 0.023717021 | F5: 29.793078 | G5: 3.9681807 | H5: 4117 | K5: Central | L5: 2234 | M5: 157636 | P5: 2011 | Q5: 54487 | R5: 753 | U5: Jan | V5: 17507 | W5: 257 | Z5: Furniture | AA5: 49734 | AB5: 1238 | AE5: Avery Index Tab, Clear | AF5: 81 | AI5: Cuisinart Microwave, Black | AJ5: 1 | AM5: Accessories | AN5: 26830 | AO5: 5137.1 | AR5: Consumer | AS5: 147447 | AT5: 2132 | AW5: Aaron Bootman | AX5: 11 | BA5: Economy | BB5: 2445
K6: North | L6: 950 | M6: 71439 | P6: 2012 | Q6: 66223 | R6: 946 | U6: Feb | V6: 14482 | W6: 220 | Z6: Office Supplies | AA6: 124952 | AB6: 5286 | AE6: Binney & Smith Sketch Pad, Blue | AF6: 90 | AI6: Cuisinart Refrigerator, White | AJ6: 1 | AM6: Appliances | AN6: 37906 | AO6: 16769.2 | AR6: Corporate | AS6: 92634 | AT6: 1268 | AW6: Georgina Garner | AX6: 11 | BA6: Economy Plus | BB6: 838
K7: South | L7: 933 | M7: 54165 | P7: 2013 | Q7: 77200 | R7: 1093 | U7: Mar | V7: 12930 | W7: 248 | Z7: Technology | AA7: 108554 | AB7: 1523 | AE7: Boston Canvas, Fluorescent | AF7: 73 | AI7: Harbour Creations Bag Chairs, Set of Two | AJ7: 1 | AM7: Art | AN7: 23491 | AO7: 5462.6 | AR7: Home Office | AS7: 43159 | AT7: 717 | AW7: Hayden Perkins | AX7: 11 | BA7: Immediate | BB7: 217
K8: Grand Total | L8: 4117 | M8: 283240 | P8: 2014 | Q8: 85330 | R8: 1325 | U8: Apr | V8: 16004 | W8: 238 | Z8: Grand Total | AA8: 283240 | AB8: 8047 | AE8: Boston Pencil Sharpener, Water Color | AF8: 80 | AI8: Jiffy Manila Envelope, Recycled | AJ8: 1 | AM8: Binders | AN8: 14703 | AO8: 3664 | AR8: Grand Total | AS8: 283240 | AT8: 4117 | AW8: Jason Roger | AX8: 11 | BA8: Priority | BB8: 617
P9: Grand Total | Q9: 283240 | R9: 4117 | U9: May | V9: 16171 | W9: 239 | AE9: Eldon File Cart, Single Width | AF9: 104 | AI9: Lesro Training Table, Adjustable Height | AJ9: 1 | AM9: Bookcases | AN9: 43655 | AO9: 27738.3 | AW9: Jessica Paramor | AX9: 11 | BA9: Grand Total | BB9: 4117
U10: Jun | V10: 31797 | W10: 444 | AE10: Ibico Index Tab, Clear | AF10: 72 | AI10: Office Star Chairmat, Set of Two | AJ10: 1 | AM10: Chairs | AN10: 15489 | AO10: 26170.8 | AW10: Jose Gambino | AX10: 13
U11: Jul | V11: 16694 | W11: 231 | AE11: Rogers File Cart, Single Width | AF11: 108 | AI11: Panasonic Card Printer, Wireless | AJ11: 1 | AM11: Copiers | AN11: 42775 | AO11: 21738.9 | AW11: Kayla Tearle | AX11: 12
U12: Aug | V12: 38486 | W12: 561 | AE12: Sanford Markers, Water Color | AF12: 75 | AI12: Sauder Stackable Bookrack, Mobile | AJ12: 1 | AM12: Envelopes | AN12: 6463 | AO12: 1211.4 | AW12: Lilly Le Grand | AX12: 11
U13: Sep | V13: 37423 | W13: 487 | AE13: Stanley Pencil Sharpener, Water Color | AF13: 89 | AI13: Stiletto Shears, Steel | AJ13: 1 | AM13: Fasteners | AN13: 3420 | AO13: 892.7 | AW13: Lori Miller | AX13: 11
U14: Oct | V14: 19110 | W14: 236 | AE14: Tenex File Cart, Single Width | AF14: 78 | AI14: Xerox Message Books, Multicolor | AJ14: 1 | AM14: Furnishings | AN14: 11321 | AO14: 4020.6 | AW14: Mark Washington | AX14: 12
U15: Nov | V15: 28533 | W15: 470 | AE15: Grand Total | AF15: 850 | AI15: Grand Total | AJ15: 10 | AM15: Labels | AN15: 2636 | AO15: 463.3 | AW15: Grand Total | AX15: 114
U16: Dec | V16: 34103 | W16: 486 | AM16: Machines | AN16: 11318 | AO16: 21712.05
U17: Grand Total | V17: 283240 | W17: 4117 | AM17: Paper | AN17: 7485 | AO17: 1229.7
AM18: Phones | AN18: 27631 | AO18: 35209.75
AM19: Storage | AN19: 21995 | AO19: 38121.9
AM20: Supplies | AN20: 6853 | AO20: 1657
AM21: Tables | AN21: -20731 | AO21: 28545.6
AM22: Grand Total | AN22: 283240 | AO22: 239744.9

Sheet Dashboard1
B1: Total Sales | D1: =GETPIVOTDATA("[Measures].[Sum of Order Value]",Sheet1!$A$4) -> 11942478 | F1: Total Profits | H1: =GETPIVOTDATA("[Measures].[Sum of Profit]",Sheet1!$A$4) -> 283240 | J1: Total Quantities | L1: =GETPIVOTDATA("[Measures].[Sum of Quantity]",Sheet1!$A$4) -> 30354 | N1: Average Of Orders | P1: =GETPIVOTDATA("[Measures].[Average of Order Value]",Sheet1!$A$4) -> 1484.0907 | R1: Profit Margin | T1: =GETPIVOTDATA("[Measures].[Profit margin_(%)]",Sheet1!$A$4) -> 0.023717021 | V1: Average of Discount | X1: =GETPIVOTDATA("[Measures].[Average of Discount Value]",Sheet1!$A$4) -> 29.793078 | Z1: Average of Shipping Duration | AB1: =GETPIVOTDATA("[Measures].[Average of Shipping Duration]",Sheet1!$A$4) -> 3.9681807

Sheet Dashboard 2
B1: Total Sales | D1: =GETPIVOTDATA("[Measures].[Sum of Order Value]",Sheet1!$A$4) -> 11942478 | F1: Total Profits | H1: =GETPIVOTDATA("[Measures].[Sum of Profit]",Sheet1!$A$4) -> 283240 | J1: Total Quantities | L1: =GETPIVOTDATA("[Measures].[Sum of Quantity]",Sheet1!$A$4) -> 30354 | N1: Average Of Orders | P1: =GETPIVOTDATA("[Measures].[Average of Order Value]",Sheet1!$A$4) -> 1484.0907 | R1: Profit Margin | T1: =GETPIVOTDATA("[Measures].[Profit margin_(%)]",Sheet1!$A$4) -> 0.023717021 | V1: Average of Discount | X1: =GETPIVOTDATA("[Measures].[Average of Discount Value]",Sheet1!$A$4) -> 29.793078 | Z1: Average of Shipping Duration | AB1: =GETPIVOTDATA("[Measures].[Average of Shipping Duration]",Sheet1!$A$4) -> 3.9681807

Sheet Dashboard 3
B1: Total Sales | D1: =GETPIVOTDATA("[Measures].[Sum of Order Value]",Sheet1!$A$4) -> 11942478 | F1: Total Profits | H1: =GETPIVOTDATA("[Measures].[Sum of Profit]",Sheet1!$A$4) -> 283240 | J1: Total Quantities | L1: =GETPIVOTDATA("[Measures].[Sum of Quantity]",Sheet1!$A$4) -> 30354 | N1: Average Of Orders | P1: =GETPIVOTDATA("[Measures].[Average of Order Value]",Sheet1!$A$4) -> 1484.0907 | R1: Profit Margin | T1: =GETPIVOTDATA("[Measures].[Profit margin_(%)]",Sheet1!$A$4) -> 0.023717021 | V1: Average of Discount | X1: =GETPIVOTDATA("[Measures].[Average of Discount Value]",Sheet1!$A$4) -> 29.793078 | Z1: Average of Shipping Duration | AB1: =GETPIVOTDATA("[Measures].[Average of Shipping Duration]",Sheet1!$A$4) -> 3.9681807
